matrix_common/__init__.py
matrix_common/py.typed
matrix_common/regex.py
matrix_common/versionstring.py
matrix_common-1.2.1.dist-info/LICENSE
matrix_common-1.2.1.dist-info/METADATA
matrix_common-1.2.1.dist-info/WHEEL
matrix_common-1.2.1.dist-info/top_level.txt
matrix_common-1.2.1.dist-info/RECORD
