Metadata-Version: 2.1
Name: matrix-common
Version: 1.2.1
Summary: Common utilities for Synapse, Sydent and Sygnal
Home-page: https://github.com/matrix-org/matrix-python-common
Classifier: License :: OSI Approved :: Apache Software License
Requires-Python: >=3.6
License-File: LICENSE
Requires-Dist: attrs
Requires-Dist: importlib-metadata (>=1.4) ; python_version < "3.8"
Provides-Extra: dev
Requires-Dist: tox ; extra == 'dev'
Requires-Dist: twisted ; extra == 'dev'
Requires-Dist: aiounittest ; extra == 'dev'
Requires-Dist: mypy (==0.910) ; extra == 'dev'
Requires-Dist: black (==22.3.0) ; extra == 'dev'
Requires-Dist: flake8 (==4.0.1) ; extra == 'dev'
Requires-Dist: isort (==5.9.3) ; extra == 'dev'
Requires-Dist: build (==0.8.0) ; extra == 'dev'
Requires-Dist: twine (==4.0.1) ; extra == 'dev'
Provides-Extra: test
Requires-Dist: tox ; extra == 'test'
Requires-Dist: twisted ; extra == 'test'
Requires-Dist: aiounittest ; extra == 'test'
